Metadata-Version: 2.1
Name: example-app-cris
Version: 0.0.22
Summary: A small example package
Author: Cristina Garcia
Author-email: crisgarciarodriguez04@gmail.com
Requires-Python: >=3.9
Requires-Dist: coloredlogs
